timelineomat.py
timelineomat-0.7.0.dist-info/METADATA
timelineomat-0.7.0.dist-info/WHEEL
timelineomat-0.7.0.dist-info/licenses/LICENSE
timelineomat-0.7.0.dist-info/RECORD
