Metadata-Version: 2.3
Name: timelineomat
Version: 0.7.0
Summary: Squeeze events into timelines and other timeline manipulations
Author-email: Alexander Kaftan <devkral@web.de>
License-Expression: MIT
License-File: LICENSE
Keywords: database,event,time,timelines
Classifier: Development Status :: 4 - Beta
Classifier: Intended Audience :: Developers
Classifier: License :: OSI Approved :: MIT License
Classifier: Operating System :: OS Independent
Classifier: Programming Language :: Python
Classifier: Programming Language :: Python :: 3
Classifier: Topic :: Software Development
Classifier: Topic :: Software Development :: Libraries
Classifier: Topic :: Software Development :: Libraries :: Application Frameworks
Classifier: Topic :: Software Development :: Libraries :: Python Modules
Classifier: Typing :: Typed
Requires-Python: >=3.9
